enumchoice/__init__.py
enumchoice-0.0.1.dist-info/LICENSE
enumchoice-0.0.1.dist-info/METADATA
enumchoice-0.0.1.dist-info/WHEEL
enumchoice-0.0.1.dist-info/top_level.txt
enumchoice-0.0.1.dist-info/RECORD
